[
  {
    "titulo": "Convocatoria a concursos 2025",
    "fecha": "2025-09-15",
    "link": "https://docentesbrown.github.io/concursos_superior/",
    "resumen": "Se publicaron nuevas bases y condiciones.",
    "img": ""
  },
  {
    "titulo": "Lanzamos la Calculadora Salarial",
    "fecha": "2025-07-20",
    "link": "https://docentesbrown.github.io/Calculadora.Salarial.Docentes.Brown/",
    "resumen": "Herramienta abierta y colaborativa.",
    "img": ""
  },
  {
    "titulo": "Buscador de particulares actualizado",
    "fecha": "2025-08-25",
    "link": "https://docentesbrown.github.io/buscador.particular/",
    "resumen": "Nuevos filtros y mejoras de velocidad.",
    "img": ""
  }
]
